agente/__init__.py
agente/_version.py
agente/core/__init__.py
agente/core/base.py
agente/core/decorators.py
agente/core/exceptions.py
agente/models/__init__.py
agente/models/schemas.py
agente-0.3.2.dist-info/licenses/LICENSE
agente-0.3.2.dist-info/METADATA
agente-0.3.2.dist-info/WHEEL
agente-0.3.2.dist-info/top_level.txt
agente-0.3.2.dist-info/RECORD
