Metadata-Version: 2.4
Name: agente
Version: 0.3.2
Summary: A very simple Python framework for building AI Agents
Author-email: Miguel Won <miguelwon@gmail.com>
License:                                  Apache License
Classifier: Programming Language :: Python :: 3
Classifier: License :: OSI Approved :: Apache Software License
Classifier: Operating System :: OS Independent
Requires-Python: >=3.9
License-File: LICENSE
Requires-Dist: litellm<2.0.0,>=1.70.0
Requires-Dist: pydantic<3.0.0,>=2.8.0
Requires-Dist: langchain-core<2.0.0,>=1.0.0
Provides-Extra: examples
Requires-Dist: python-dotenv<2.0.0,>=1.0.0; extra == "examples"
Requires-Dist: gradio<6.0.0,>=5.0.0; extra == "examples"
Dynamic: license-file
